global_macro_data/__init__.py
global_macro_data/gmd.py
global_macro_data-0.3.1.dist-info/METADATA
global_macro_data-0.3.1.dist-info/WHEEL
global_macro_data-0.3.1.dist-info/top_level.txt
global_macro_data-0.3.1.dist-info/RECORD
