Metadata-Version: 2.4
Name: global-macro-data
Version: 0.3.1
Summary: Global Macro Database by Karsten Müller, Chenzi Xu, Mohamed Lehbib and Ziliang Chen (2025)
Home-page: https://github.com/KMueller-Lab/Global-Macro-Database-Python
Author: Yangbo Wang
Author-email: wangyangbo@ruc.edu.cn
Classifier: Programming Language :: Python :: 3
Classifier: License :: OSI Approved :: MIT License
Classifier: Operating System :: OS Independent
Requires-Python: >=3.6
Requires-Dist: requests
Requires-Dist: pandas
Dynamic: author
Dynamic: author-email
Dynamic: classifier
Dynamic: description
Dynamic: description-content-type
Dynamic: home-page
Dynamic: requires-dist
Dynamic: requires-python
Dynamic: summary
